lasagnamail/__init__.py
lasagnamail/email.py
lasagnamail-0.0.1.dist-info/LICENSE
lasagnamail-0.0.1.dist-info/METADATA
lasagnamail-0.0.1.dist-info/WHEEL
lasagnamail-0.0.1.dist-info/top_level.txt
lasagnamail-0.0.1.dist-info/RECORD
